langagent/__init__.py
langagent/business_intelligence_team/__init__.py
langagent/business_intelligence_team/agents/__init__.py
langagent/business_intelligence_team/agents/bi_analyst_agent.py
langagent/data_science_team/__init__.py
langagent/data_science_team/agents/__init__.py
langagent/data_science_team/agents/data_cleaning_agent.py
langagent/data_science_team/agents/data_wrangling_agent.py
langagent/data_science_team/agents/feature_engineering_agent.py
langagent/data_science_team/agents/sql_database_agent.py
langagent/data_science_team/templates/__init__.py
langagent/data_science_team/templates/agent_templates.py
langagent/data_science_team/tools/__init__.py
langagent/data_science_team/tools/logging.py
langagent/data_science_team/tools/metadata.py
langagent/data_science_team/tools/parsers.py
langagent/data_science_team/tools/regex.py
langagent/logic_team/__init__.py
langagent/logic_team/agents/__init__.py
langagent/logic_team/agents/calculator.py
langagent/logic_team/agents/reasoner.py
langagent/reporting_team/__init__.py
langagent/reporting_team/agents/__init__.py
langagent/reporting_team/agents/interpreter.py
langagent/reporting_team/agents/summarizer.py
langagent/research_team/__init__.py
langagent/research_team/agents/__init__.py
langagent/research_team/agents/coder.py
langagent/research_team/agents/researcher.py
langagent/research_team/agents/weather.py
langagent/supervisor/__init__.py
langagent/supervisor/supervisor_chain.py
langagent/text_clustering_team/__init__.py
langagent/text_clustering_team/agents/__init__.py
langagent/text_clustering_team/agents/topic_generator.py
langagent/trading_team/__init__.py
langagent/trading_team/agents/__init__.py
langagent/trading_team/agents/fundamentals_analyst.py
langagent/trading_team/agents/portfolio_manager.py
langagent/trading_team/agents/risk_manager.py
langagent/trading_team/agents/sentiments_analyst.py
langagent/trading_team/agents/technicals_analyst.py
langagent/trading_team/agents/valuations_analyst.py
langagent-3.2.1.dist-info/METADATA
langagent-3.2.1.dist-info/WHEEL
langagent-3.2.1.dist-info/top_level.txt
langagent-3.2.1.dist-info/RECORD
