Metadata-Version: 2.2
Name: langagent
Version: 3.2.1
Summary: LangAgent is a powerful multi-agent system designed to automate and streamline complex tasks, including research, automated code generation, logical reasoning, data analysis, business intelligence, trading insights, and dynamic reporting. 
Home-page: https://github.com/knowusuboaky/LangAgent
Author: Kwadwo Daddy Nyame Owusu - Boakye
Author-email: kwadwo.owusuboakye@outlook.com
License: MIT
Keywords: AI,machine learning,language models,multi-agent systems,research automation,code generation,data analysis,reasoning,reporting,LangChain,LangSmith,Python,SQL,data visualization,automation,OpenAI,data science,natural language processing,deep learning,document summarization,web scraping,APIs,business intelligence,feature engineering,data preprocessing,workflow optimization,predictive modeling,database querying,data pipelines,generative AI,semantic search,vector embeddings,knowledge graphs
Classifier: Programming Language :: Python :: 3
Classifier: License :: OSI Approved :: MIT License
Classifier: Operating System :: OS Independent
Requires-Python: >=3.10
Requires-Dist: langchain==0.1.16
Requires-Dist: langchain-community==0.0.33
Requires-Dist: langchain-core==0.1.52
Requires-Dist: langchain-experimental==0.0.57
Requires-Dist: langchain-groq==0.1.3
Requires-Dist: langchain-openai==0.0.8
Requires-Dist: langchain-text-splitters==0.0.1
Requires-Dist: langgraph==0.0.48
Requires-Dist: langsmith==0.1.27
Requires-Dist: tavily-python
Requires-Dist: sentence-transformers>=2.2.2
Requires-Dist: ipython==8.18.0
Requires-Dist: ipywidgets==8.1.2
Requires-Dist: nbformat>=4.2.0
Requires-Dist: plotly>=5.0.0
Requires-Dist: matplotlib>=3.5.0
Requires-Dist: seaborn>=0.11.2
Requires-Dist: tqdm>=4.0.0
Requires-Dist: pandas
Requires-Dist: numpy
Requires-Dist: scikit-learn>=0.24.0
Requires-Dist: numexpr>=2.8.4
Requires-Dist: altair==4.1.0
Requires-Dist: ppscore==1.2.0
Requires-Dist: pyjanitor==0.20.14
Requires-Dist: requests>=2.25.1
Requires-Dist: beautifulsoup4>=4.9.3
Requires-Dist: pyowm>=3.3.0
Requires-Dist: kubernetes==29.0.0
Requires-Dist: yfinance>=0.1.0
Requires-Dist: quantstats
Requires-Dist: PyYAML>=6.0
Requires-Dist: pypdf2>=3.0.0
Requires-Dist: python-pptx>=0.6.21
Requires-Dist: python-docx>=0.8.11
Requires-Dist: xlsxwriter==1.3.7
Requires-Dist: openpyxl
Requires-Dist: sqlalchemy>=2.0.0
Requires-Dist: sqlite-utils
Requires-Dist: pymysql
Requires-Dist: psycopg2
Dynamic: author
Dynamic: author-email
Dynamic: classifier
Dynamic: description
Dynamic: description-content-type
Dynamic: home-page
Dynamic: keywords
Dynamic: license
Dynamic: requires-dist
Dynamic: requires-python
Dynamic: summary
